rudderclient/__init__.py
rudderclient/aws/__init__.py
rudderclient/aws/requests.py
rudderclient/azure/__init__.py
rudderclient/azure/requests.py
rudderclient/gcp/__init__.py
rudderclient/gcp/auth.py
rudderclient/gcp/http_requests.py
rudderclient/gcp/iam.py
rudderclient/gcp/pubsub.py
rudderclient/gcp/secrets.py
rudderclient/gcp/security_policies.py
rudderclient/gcp/workspace.py
rudderclient/github/__init__.py
rudderclient/github/https_requests.py
rudderclient/logger/__init__.py
rudderclient/logger/logger.py
rudderclient/request/__init__.py
rudderclient/request/exceptions.py
rudderclient/request/helpers.py
rudderclient/tools/send_email.py
rudderclient-1.20.0.dist-info/LICENSE
rudderclient-1.20.0.dist-info/METADATA
rudderclient-1.20.0.dist-info/WHEEL
rudderclient-1.20.0.dist-info/top_level.txt
rudderclient-1.20.0.dist-info/RECORD
