Metadata-Version: 2.1
Name: rudderclient
Version: 1.20.0
Summary: Shared helpers for rudder application functions code
Author-email: Rudder Team <rudder@realnaut.com>
License: MIT License
Project-URL: Homepage, https://github.com/realnautops/rudder-client
Keywords: rudder,client,helper
Classifier: License :: OSI Approved :: MIT License
Classifier: Programming Language :: Python
Classifier: Programming Language :: Python :: 3.10
Requires-Python: >=3.10
License-File: LICENSE
Requires-Dist: google-cloud-secret-manager
